README.md
setup.cfg
setup.py
skrobot/__init__.py
skrobot.egg-info/PKG-INFO
skrobot.egg-info/SOURCES.txt
skrobot.egg-info/dependency_links.txt
skrobot.egg-info/requires.txt
skrobot.egg-info/top_level.txt
skrobot/core/__init__.py
skrobot/core/experiment.py
skrobot/core/task_runner.py
skrobot/feature_selection/__init__.py
skrobot/feature_selection/column_selector.py
skrobot/notification/__init__.py
skrobot/notification/base_notifier.py
skrobot/notification/email_notifier.py
skrobot/tasks/__init__.py
skrobot/tasks/base_cross_validation_task.py
skrobot/tasks/base_task.py
skrobot/tasks/dataset_calculation_task.py
skrobot/tasks/deep_feature_synthesis_task.py
skrobot/tasks/evaluation_cross_validation_task.py
skrobot/tasks/feature_selection_cross_validation_task.py
skrobot/tasks/hyperparameters_search_cross_validation_task.py
skrobot/tasks/prediction_task.py
skrobot/tasks/train_task.py