Metadata-Version: 2.1
Name: skrobot
Version: 1.0.13
Summary: skrobot is a Python module for designing, running and tracking Machine Learning experiments / tasks. It is built on top of scikit-learn framework.
Home-page: https://github.com/medoidai/skrobot
Author: Medoid AI
Author-email: info@medoid.ai
License: MIT
Download-URL: https://github.com/medoidai/skrobot/archive/1.0.13.tar.gz
Platform: any
Classifier: Development Status :: 5 - Production/Stable
Classifier: Intended Audience :: Developers
Classifier: Intended Audience :: Education
Classifier: Intended Audience :: Science/Research
Classifier: Operating System :: OS Independent
Classifier: License :: OSI Approved :: MIT License
Classifier: Programming Language :: Python
Classifier: Programming Language :: Python :: 3
Classifier: Programming Language :: Python :: 3.6
Classifier: Programming Language :: Python :: 3.7
Classifier: Programming Language :: Python :: 3.8
Classifier: Topic :: Scientific/Engineering
Classifier: Topic :: Scientific/Engineering :: Artificial Intelligence
Classifier: Environment :: Console
Requires-Python: >=3.6
